<?xml version='1.0' encoding='UTF-8'?>
<!DOCTYPE Identity PUBLIC "sailpoint.dtd" "sailpoint.dtd">
<Identity correlated="true" lastRefresh="1779186116046" name="Denise Hunt">
  <Attributes>
    <Map>
      <entry key="department" value="Finance"/>
      <entry key="displayName" value="Denise Hunt"/>
      <entry key="email" value="Denise.Hunt@eshiam.com"/>
      <entry key="employeeId" value="1b2c3d4a"/>
      <entry key="firstname" value="Denise"/>
      <entry key="lastname" value="Hunt"/>
      <entry key="networkId" value="Denise.Hunt"/>
      <entry key="pendingRefreshWorkflow" value="Refresh identity Denise Hunt"/>
      <entry key="triggerSnapshots">
        <value>
          <Map>
            <entry key="NativeChange">
              <value>
                <List>
                  <NativeChangeDetection application="ActiveDirectory" identity="CN=Denise Hunt,OU=People,OU=Demo,DC=Eshiam,DC=com" lastRefresh="1766136094078" operation="Create" simpleIdentity="1b2c3d4a">
                    <Attributes>
                      <Map>
                        <entry key="NetBIOSName"/>
                        <entry key="accountFlags">
                          <value>
                            <List>
                              <String>Normal User Account</String>
                            </List>
                          </value>
                        </entry>
                        <entry key="cn" value="Denise Hunt"/>
                        <entry key="department" value="Finance"/>
                        <entry key="displayName" value="Hunt, Denise"/>
                        <entry key="distinguishedName" value="CN=Denise Hunt,OU=People,OU=Demo,DC=Eshiam,DC=com"/>
                        <entry key="employeeID" value="1b2c3d4a"/>
                        <entry key="givenName" value="Denise"/>
                        <entry key="mail" value="Denise.Hunt@eshiam.com"/>
                        <entry key="memberOf"/>
                        <entry key="msDS-PrincipalName" value="ESHIAM\Denise Hunt"/>
                        <entry key="msNPAllowDialin" value="Not Set"/>
                        <entry key="objectClass">
                          <value>
                            <List>
                              <String>top</String>
                              <String>person</String>
                              <String>organizationalPerson</String>
                              <String>user</String>
                            </List>
                          </value>
                        </entry>
                        <entry key="objectSid" value="S-1-5-21-2678700903-2778472132-3948167259-1316"/>
                        <entry key="objectType" value="user"/>
                        <entry key="objectguid" value="{3e1311ef-01c6-46ed-8c08-cab83951b6a1}"/>
                        <entry key="sAMAccountName" value="Denise Hunt"/>
                        <entry key="sn" value="Hunt"/>
                        <entry key="userPrincipalName" value="Denise Hunt@test.eshiam.com"/>
                      </Map>
                    </Attributes>
                    <Differences>
                      <Difference attribute="cn" displayName="cn" newValue="Denise Hunt"/>
                      <Difference attribute="sAMAccountName" displayName="sAMAccountName" newValue="Denise Hunt"/>
                      <Difference attribute="mail" displayName="mail" newValue="Denise.Hunt@eshiam.com"/>
                    </Differences>
                  </NativeChangeDetection>
                </List>
              </value>
            </entry>
          </Map>
        </value>
      </entry>
      <entry key="type" value="employee"/>
    </Map>
  </Attributes>
  <AttributeMetaDatas>
    <AttributeMetaData attribute="displayName" source="HR-Application:Name"/>
    <AttributeMetaData attribute="email" source="HR-Application:Email"/>
    <AttributeMetaData attribute="firstname" source="HR-Application:FirstName"/>
    <AttributeMetaData attribute="lastname" source="HR-Application:LastName"/>
    <AttributeMetaData attribute="employeeId" source="HR-Application:EmployeeNo"/>
    <AttributeMetaData attribute="department" source="HR-Application:Department"/>
    <AttributeMetaData attribute="networkId" source="HR-Application:NetworkID"/>
    <AttributeMetaData attribute="manager" source="HR-Application:manager"/>
    <AttributeMetaData attribute="costCenter" source="CyberSolveTask:costcenter"/>
    <AttributeMetaData attribute="region" source="CyberSolveTask:region"/>
    <AttributeMetaData attribute="type" source="HR Employees TRNG:AppRule: TRNG-IdentityAttribute-Employee HR Employees TRNG$TRNG-IdentityAttribute-Employee"/>
    <AttributeMetaData attribute="inactive" source="SRH application:inactive"/>
  </AttributeMetaDatas>
  <Manager>
    <Reference class="sailpoint.object.Identity" name="Catherine Simmons"/>
  </Manager>
  <Preferences>
    <Map>
      <entry key="roleAssignments"/>
    </Map>
  </Preferences>
  <Links>
    <Link displayName="Denise Hunt" identity="1b2c3d4a" lastRefresh="1714615486117">
      <ApplicationRef>
        <Reference class="sailpoint.object.Application" name="HR-ApplicationTarget"/>
      </ApplicationRef>
      <Attributes>
        <Map>
          <entry key="Department" value="Finance"/>
          <entry key="Email" value="Denise.Hunt@eshiam.com"/>
          <entry key="EmployeeNo" value="1b2c3d4a"/>
          <entry key="FirstName" value="Denise"/>
          <entry key="LastName" value="Hunt"/>
          <entry key="Name" value="Denise Hunt"/>
          <entry key="NetworkID" value="Denise.Hunt"/>
          <entry key="manager" value="1b2c3d"/>
        </Map>
      </Attributes>
    </Link>
    <Link displayName="Denise Hunt" identity="1b2c3d4a" lastRefresh="1714616260213">
      <ApplicationRef>
        <Reference class="sailpoint.object.Application" name="JDBC"/>
      </ApplicationRef>
      <Attributes>
        <Map>
          <entry key="Department" value="Finance"/>
          <entry key="Email" value="Denise.Hunt@eshiam.com"/>
          <entry key="EmployeeNo" value="1b2c3d4a"/>
          <entry key="FirstName" value="Denise"/>
          <entry key="LastName" value="Hunt"/>
          <entry key="Name" value="Denise Hunt"/>
          <entry key="NetworkID" value="Denise.Hunt"/>
          <entry key="manager" value="1b2c3d"/>
        </Map>
      </Attributes>
    </Link>
    <Link displayName="Denise Hunt" identity="CN=Denise Hunt,OU=People,OU=Demo,DC=Eshiam,DC=com" lastRefresh="1779698519521" uuid="{3e1311ef-01c6-46ed-8c08-cab83951b6a1}">
      <ApplicationRef>
        <Reference class="sailpoint.object.Application" name="ActiveDirectory"/>
      </ApplicationRef>
      <Attributes>
        <Map>
          <entry key="NetBIOSName"/>
          <entry key="accountFlags">
            <value>
              <List>
                <String>Normal User Account</String>
              </List>
            </value>
          </entry>
          <entry key="cn" value="Denise Hunt"/>
          <entry key="department" value="Finance"/>
          <entry key="displayName" value="Hunt, Denise"/>
          <entry key="distinguishedName" value="CN=Denise Hunt,OU=People,OU=Demo,DC=Eshiam,DC=com"/>
          <entry key="employeeID" value="1b2c3d4a"/>
          <entry key="givenName" value="Denise"/>
          <entry key="mail" value="Finance"/>
          <entry key="memberOf"/>
          <entry key="msDS-PrincipalName" value="ESHIAM\Denise Hunt"/>
          <entry key="msNPAllowDialin" value="Not Set"/>
          <entry key="objectClass">
            <value>
              <List>
                <String>top</String>
                <String>person</String>
                <String>organizationalPerson</String>
                <String>user</String>
              </List>
            </value>
          </entry>
          <entry key="objectSid" value="S-1-5-21-2678700903-2778472132-3948167259-1316"/>
          <entry key="objectType" value="user"/>
          <entry key="objectguid" value="{3e1311ef-01c6-46ed-8c08-cab83951b6a1}"/>
          <entry key="sAMAccountName" value="Denise Hunt"/>
          <entry key="sn" value="Hunt"/>
          <entry key="userPrincipalName" value="Denise Hunt@test.eshiam.com"/>
        </Map>
      </Attributes>
    </Link>
    <Link displayName="Denise Hunt" identity="Denise Hunt" lastRefresh="1767083091652">
      <ApplicationRef>
        <Reference class="sailpoint.object.Application" name="SCIMApp"/>
      </ApplicationRef>
      <Attributes>
        <Map>
          <entry key="IIQDisabled">
            <value>
              <Boolean/>
            </value>
          </entry>
          <entry key="accounts">
            <value>
              <List>
                <String>{"displayName":"Denise Hunt","value":"c0a800208f361ec2818f370c06a400be","$ref":"http://localhost:8080/identityiq-8.4/scim/v2/Accounts/c0a800208f361ec2818f370c06a400be"}</String>
                <String>{"displayName":"Denise Hunt","value":"c0a800208f361ec2818f3717d67501d1","$ref":"http://localhost:8080/identityiq-8.4/scim/v2/Accounts/c0a800208f361ec2818f3717d67501d1"}</String>
                <String>{"displayName":"Denise Hunt","value":"c0a801199b34190d819b35ea1d7e02e3","$ref":"http://localhost:8080/identityiq-8.4/scim/v2/Accounts/c0a801199b34190d819b35ea1d7e02e3"}</String>
                <String>{"displayName":"Denise Hunt","value":"c0a801199b581419819b6a707e9717ab","$ref":"http://localhost:8080/identityiq-8.4/scim/v2/Accounts/c0a801199b581419819b6a707e9717ab"}</String>
                <String>{"displayName":"Denise Hunt","value":"c0a81d898f331f7b818f3404c05f013f","$ref":"http://localhost:8080/identityiq-8.4/scim/v2/Accounts/c0a81d898f331f7b818f3404c05f013f"}</String>
              </List>
            </value>
          </entry>
          <entry key="active">
            <value>
              <Boolean>true</Boolean>
            </value>
          </entry>
          <entry key="department" value="Finance"/>
          <entry key="displayName" value="Denise Hunt"/>
          <entry key="emails.work.primary.value" value="Denise.Hunt@eshiam.com"/>
          <entry key="id" value="Denise Hunt"/>
          <entry key="isManager">
            <value>
              <Boolean/>
            </value>
          </entry>
          <entry key="lastRefresh">
            <value>
              <Date>1767017316007</Date>
            </value>
          </entry>
          <entry key="manager">
            <value>
              <Map>
                <entry key="$ref" value="http://localhost:8080/identityiq-8.4/scim/v2/Users/Catherine Simmons"/>
                <entry key="displayName" value="Catherine Simmons"/>
                <entry key="value" value="Catherine Simmons"/>
              </Map>
            </value>
          </entry>
          <entry key="name.familyName" value="Hunt"/>
          <entry key="name.formatted" value="Denise Hunt"/>
          <entry key="name.givenName" value="Denise"/>
          <entry key="networkId" value="Denise.Hunt"/>
          <entry key="riskScore">
            <value>
              <Integer>0</Integer>
            </value>
          </entry>
          <entry key="userName" value="Denise Hunt"/>
          <entry key="userType" value="employee"/>
        </Map>
      </Attributes>
    </Link>
    <Link displayName="Denise.Hunt" identity="cn=Denise.Hunt,ou=People,dc=my-domain,dc=com" lastRefresh="1770702083757">
      <ApplicationRef>
        <Reference class="sailpoint.object.Application" name="LDAPApplication"/>
      </ApplicationRef>
      <Attributes>
        <Map>
          <entry key="IIQDisabled">
            <value>
              <Boolean/>
            </value>
          </entry>
          <entry key="cn" value="Denise.Hunt"/>
          <entry key="dn" value="cn=Denise.Hunt,ou=People,dc=my-domain,dc=com"/>
          <entry key="objectClass">
            <value>
              <List>
                <String>inetOrgPerson</String>
              </List>
            </value>
          </entry>
          <entry key="sn" value="Hunt"/>
        </Map>
      </Attributes>
    </Link>
    <Link displayName="Denise Hunt" identity="1b2c3d4a" lastRefresh="1714564677727">
      <ApplicationRef>
        <Reference class="sailpoint.object.Application" name="HR-Application"/>
      </ApplicationRef>
      <Attributes>
        <Map>
          <entry key="Department" value="Finance"/>
          <entry key="Email" value="Denise.Hunt@eshiam.com"/>
          <entry key="EmployeeNo" value="1b2c3d4a"/>
          <entry key="FirstName" value="Denise"/>
          <entry key="LastName" value="Hunt"/>
          <entry key="Name" value="Denise Hunt"/>
          <entry key="NetworkID" value="Denise.Hunt"/>
          <entry key="manager" value="1b2c3d"/>
        </Map>
      </Attributes>
    </Link>
  </Links>
  <Scorecard/>
</Identity>