<?xml version='1.0' encoding='UTF-8'?>
<!DOCTYPE ProvisioningTransaction PUBLIC "sailpoint.dtd" "sailpoint.dtd">
<ProvisioningTransaction accountDisplayName="Aaron Wade" applicationName="JDBCProvisioning" identityDisplayName="Aaron Wade" identityName="Aaron Wade" integration="JDBCProvisioning" name="0000008112" nativeIdentity="EMP01478" operation="Create" source="IdentityRefresh" status="Success" type="Auto">
  <Attributes>
    <Map>
      <entry key="planResult">
        <value>
          <ProvisioningResult status="committed"/>
        </value>
      </entry>
      <entry key="request">
        <value>
          <AccountRequest application="JDBCProvisioning" nativeIdentity="EMP01478" op="Create" targetIntegration="JDBCProvisioning">
            <Attributes>
              <Map>
                <entry key="provisioningTransactionId" value="c0a81d8998c11a508198c29a1c09114e"/>
              </Map>
            </Attributes>
            <AttributeRequest name="GroupName" op="Add" value="9">
              <Attributes>
                <Map>
                  <entry key="assignment">
                    <value>
                      <Boolean>true</Boolean>
                    </value>
                  </entry>
                </Map>
              </Attributes>
            </AttributeRequest>
            <AttributeRequest name="GroupName" op="Add" value="8">
              <Attributes>
                <Map>
                  <entry key="assignment">
                    <value>
                      <Boolean>true</Boolean>
                    </value>
                  </entry>
                </Map>
              </Attributes>
            </AttributeRequest>
            <AttributeRequest name="Name" op="Set" value="Aaron Wade"/>
            <AttributeRequest name="FirstName" op="Set" value="Aaron"/>
            <AttributeRequest name="LastName" op="Set" value="Wade"/>
            <AttributeRequest name="Department" op="Set" value="Sales"/>
            <AttributeRequest name="EmailAddress" op="Set" value="aaron.wade@example.com"/>
            <AttributeRequest name="NetworkID" op="Set" value="Aaron.Wade"/>
            <AttributeRequest name="managerID" op="Set" value="1045"/>
            <ProvisioningResult status="committed"/>
          </AccountRequest>
        </value>
      </entry>
    </Map>
  </Attributes>
</ProvisioningTransaction>