<?xml version='1.0' encoding='UTF-8'?>
<!DOCTYPE ProvisioningTransaction PUBLIC "sailpoint.dtd" "sailpoint.dtd">
<ProvisioningTransaction accountDisplayName="Abigail White" applicationName="IdentityIQ" identityDisplayName="Abigail White" identityName="Abigail White" integration="IdentityIQ" name="0000010505" nativeIdentity="Abigail White" operation="Modify" source="Rule" status="Success" type="Auto">
  <Attributes>
    <Map>
      <entry key="request">
        <value>
          <AccountRequest application="IIQ" op="Modify" targetIntegration="IIQ">
            <Attributes>
              <Map>
                <entry key="provisioningTransactionId" value="c0a801289c451b3a819c465e1e4f084e"/>
              </Map>
            </Attributes>
            <AttributeRequest name="assignedRoles" op="Add" value="EshiamWebservices IT Role"/>
          </AccountRequest>
        </value>
      </entry>
    </Map>
  </Attributes>
</ProvisioningTransaction>