<?xml version='1.0' encoding='UTF-8'?>
<!DOCTYPE ProvisioningTransaction PUBLIC "sailpoint.dtd" "sailpoint.dtd">
<ProvisioningTransaction accountDisplayName="CN=Abigail Frey,OU=People,OU=Demo,DC=Eshiam,DC=com" applicationName="ActiveDirectory" identityDisplayName="Abigail Frey" identityName="Abigail Frey" integration="ActiveDirectory" name="0000007089" nativeIdentity="CN=Abigail Frey,OU=People,OU=Demo,DC=Eshiam,DC=com" operation="Create" source="LCM" status="Success" type="Auto">
  <Attributes>
    <Map>
      <entry key="lastRetry">
        <value>
          <Long>1751002511274</Long>
        </value>
      </entry>
      <entry key="request">
        <value>
          <AccountRequest application="ActiveDirectory" assignmentIds="4badefcb1333487e9fec1eeaccdecc74" nativeIdentity="CN=Abigail Frey,OU=People,OU=Demo,DC=Eshiam,DC=com" op="Create" targetIntegration="ActiveDirectory">
            <Attributes>
              <Map>
                <entry key="provisioningTransactionId" value="c0a8001697a21be78197afaac8f6292c"/>
              </Map>
            </Attributes>
            <AttributeRequest name="memberOf" op="Add" value="CN=AccountsReceivable,OU=Groups,OU=Demo,DC=Eshiam,DC=com"/>
            <AttributeRequest name="sAMAccountName" op="Set" value="Abigail Frey"/>
            <AttributeRequest name="givenName" op="Set" value="Abigail"/>
            <AttributeRequest name="sn" op="Set" value="Frey"/>
            <AttributeRequest name="mail" op="Set" value="abigail.frey@eshiam.com"/>
            <AttributeRequest name="password" op="Set"/>
            <ProvisioningResult status="committed"/>
          </AccountRequest>
        </value>
      </entry>
      <entry key="retryCount" value="1"/>
    </Map>
  </Attributes>
</ProvisioningTransaction>