<?xml version='1.0' encoding='UTF-8'?>
<!DOCTYPE ProvisioningTransaction PUBLIC "sailpoint.dtd" "sailpoint.dtd">
<ProvisioningTransaction accountDisplayName="Bruce Henry" applicationName="ActiveDirectory" identityDisplayName="Bruce Henry" identityName="Bruce Henry" integration="ActiveDirectory" name="0000006420" nativeIdentity="CN=Bruce Henry,OU=People,OU=Demo,DC=Eshiam,DC=com" operation="Modify" source="LCM" status="Success" type="Auto">
  <Attributes>
    <Map>
      <entry key="accessRequestId" value="0000000461"/>
      <entry key="request">
        <value>
          <AccountRequest application="ActiveDirectory" nativeIdentity="CN=Bruce Henry,OU=People,OU=Demo,DC=Eshiam,DC=com" op="Modify" targetIntegration="ActiveDirectory">
            <Attributes>
              <Map>
                <entry key="attachmentConfigList"/>
                <entry key="attachments"/>
                <entry key="flow" value="AccessRequest"/>
                <entry key="id" value="c0a800fc94cb1e358194ccac8bcd2833"/>
                <entry key="interface" value="LCM"/>
                <entry key="operation" value="EntitlementAdd"/>
                <entry key="provisioningTransactionId" value="c0a800fc94cb1e358194cf6115cc38e5"/>
              </Map>
            </Attributes>
            <AttributeRequest displayValue="AccountingGeneral" name="memberOf" op="Add" value="CN=AccountingGeneral,OU=Groups,OU=Demo,DC=Eshiam,DC=com">
              <Attributes>
                <Map>
                  <entry key="assignment" value="true"/>
                </Map>
              </Attributes>
            </AttributeRequest>
            <AttributeRequest displayValue="AccountsPayable" name="memberOf" op="Add" value="CN=AccountsPayable,OU=Groups,OU=Demo,DC=Eshiam,DC=com">
              <Attributes>
                <Map>
                  <entry key="assignment" value="true"/>
                </Map>
              </Attributes>
            </AttributeRequest>
            <AttributeRequest displayValue="Admins" name="memberOf" op="Add" value="CN=Admins,OU=Groups,OU=Demo,DC=Eshiam,DC=com">
              <Attributes>
                <Map>
                  <entry key="assignment" value="true"/>
                </Map>
              </Attributes>
            </AttributeRequest>
            <AttributeRequest displayValue="All_Users" name="memberOf" op="Add" value="CN=All_Users,OU=Groups,OU=Demo,DC=Eshiam,DC=com">
              <Attributes>
                <Map>
                  <entry key="assignment" value="true"/>
                </Map>
              </Attributes>
            </AttributeRequest>
            <AttributeRequest displayValue="Buyer" name="memberOf" op="Add" value="CN=Buyer,OU=Groups,OU=Demo,DC=Eshiam,DC=com">
              <Attributes>
                <Map>
                  <entry key="assignment" value="true"/>
                </Map>
              </Attributes>
            </AttributeRequest>
            <AttributeRequest displayValue="Contractors" name="memberOf" op="Add" value="CN=Contractors,OU=Groups,OU=Demo,DC=Eshiam,DC=com">
              <Attributes>
                <Map>
                  <entry key="assignment" value="true"/>
                </Map>
              </Attributes>
            </AttributeRequest>
            <ProvisioningResult status="committed"/>
          </AccountRequest>
        </value>
      </entry>
    </Map>
  </Attributes>
</ProvisioningTransaction>