<?xml version='1.0' encoding='UTF-8'?>
<!DOCTYPE TaskResult PUBLIC "sailpoint.dtd" "sailpoint.dtd">
<TaskResult completed="1747907538116" completionStatus="Success" launched="1747907501544" launcher="spadmin" name="QuickLink Launch for identity spadmin - 482" type="Workflow">
  <Attributes>
    <Map>
      <entry key="workflowCaseId" value="a9feffec96f31fd98196f767de64063e"/>
      <entry key="workflowProcessId"/>
      <entry key="workflowSummary">
        <value>
          <WorkflowSummary step="Stop">
            <Interactions>
              <ApprovalSummary completer="The Administrator" endDate="1747907536658" owner="spadmin" request="SecodaryIdRegistrationForm" startDate="1747907501747" state="Finished" workItemId="a9feffec96f31fd98196f767de8d063f" workItemType="Form"/>
            </Interactions>
          </WorkflowSummary>
        </value>
      </entry>
    </Map>
  </Attributes>
  <Definition>
    <Reference class="sailpoint.object.TaskDefinition" name="Workflow Launcher"/>
  </Definition>
  <Owner>
    <Reference class="sailpoint.object.Identity" name="spadmin"/>
  </Owner>
</TaskResult>