<?xml version='1.0' encoding='UTF-8'?>
<!DOCTYPE TaskResult PUBLIC "sailpoint.dtd" "sailpoint.dtd">
<TaskResult completed="1740620381920" completionStatus="Error" launched="1740488496531" launcher="spadmin" name="Update Identity Carmen Hansen AccessRequest - 4" targetClass="Identity" targetName="Carmen Hansen" type="LCM">
  <Attributes>
    <Map>
      <entry key="identityRequestId" value="0000000557"/>
      <entry key="project">
        <value>
          <ProvisioningProject identity="Carmen Hansen">
            <Attributes>
              <Map>
                <entry key="disableRetryRequest">
                  <value>
                    <Boolean>true</Boolean>
                  </value>
                </entry>
                <entry key="identityRequestId" value="0000000557"/>
                <entry key="optimisticProvisioning" value="false"/>
                <entry key="requester" value="spadmin"/>
                <entry key="source" value="LCM"/>
              </Map>
            </Attributes>
            <MasterPlan>
              <ProvisioningPlan>
                <AccountRequest application="IntConApplication" op="Modify">
                  <Attributes>
                    <Map>
                      <entry key="attachmentConfigList"/>
                      <entry key="attachments"/>
                      <entry key="flow" value="AccessRequest"/>
                      <entry key="id" value="c0a800fb95361b21819538added109f7"/>
                      <entry key="interface" value="LCM"/>
                      <entry key="nativeIdUpdated">
                        <value>
                          <Boolean>true</Boolean>
                        </value>
                      </entry>
                      <entry key="operation" value="EntitlementAdd"/>
                    </Map>
                  </Attributes>
                  <AttributeRequest displayValue="GroupName1" name="GroupId" op="Add" value="GIC1">
                    <Attributes>
                      <Map>
                        <entry key="assignment" value="true"/>
                      </Map>
                    </Attributes>
                  </AttributeRequest>
                </AccountRequest>
                <AccountRequest application="ActiveDirectory" nativeIdentity="CN=Carmen Hansen,OU=People,OU=Demo,DC=Eshiam,DC=com" op="Modify">
                  <Attributes>
                    <Map>
                      <entry key="attachmentConfigList"/>
                      <entry key="attachments"/>
                      <entry key="flow" value="AccessRequest"/>
                      <entry key="id" value="c0a800fc94cb1e358194ccac8aec282a"/>
                      <entry key="interface" value="LCM"/>
                      <entry key="operation" value="EntitlementAdd"/>
                    </Map>
                  </Attributes>
                  <AttributeRequest displayValue="AccountsReceivable" name="memberOf" op="Add" value="CN=AccountsReceivable,OU=Groups,OU=Demo,DC=Eshiam,DC=com">
                    <Attributes>
                      <Map>
                        <entry key="assignment" value="true"/>
                      </Map>
                    </Attributes>
                  </AttributeRequest>
                </AccountRequest>
                <Attributes>
                  <Map>
                    <entry key="identityRequestId" value="0000000557"/>
                    <entry key="requester" value="spadmin"/>
                    <entry key="source" value="LCM"/>
                  </Map>
                </Attributes>
                <ProvisioningTargets>
                  <ProvisioningTarget application="IntConApplication" attribute="GroupId" value="GIC1">
                    <AccountSelection applicationId="c0a8002394fb1f3081952339b50f2a6d" applicationName="IntConApplication" implicitCreate="true"/>
                  </ProvisioningTarget>
                  <ProvisioningTarget application="ActiveDirectory" attribute="memberOf" value="CN=AccountsReceivable,OU=Groups,OU=Demo,DC=Eshiam,DC=com">
                    <AccountSelection applicationId="c0a800fc94cb1e358194cc6fcd4826a9" applicationName="ActiveDirectory" selection="CN=Carmen Hansen,OU=People,OU=Demo,DC=Eshiam,DC=com">
                      <AccountInfo displayName="Carmen Hansen" nativeIdentity="CN=Carmen Hansen,OU=People,OU=Demo,DC=Eshiam,DC=com"/>
                    </AccountSelection>
                  </ProvisioningTarget>
                </ProvisioningTargets>
                <Requesters>
                  <Reference class="sailpoint.object.Identity" name="spadmin"/>
                </Requesters>
              </ProvisioningPlan>
            </MasterPlan>
            <ProvisioningPlan nativeIdentity="Carmen Hansen" targetIntegration="ActiveDirectory" trackingId="89c1864695be42d1966f928f716da187">
              <AccountRequest application="ActiveDirectory" nativeIdentity="CN=Carmen Hansen,OU=People,OU=Demo,DC=Eshiam,DC=com" op="Modify" targetIntegration="ActiveDirectory">
                <Attributes>
                  <Map>
                    <entry key="attachmentConfigList"/>
                    <entry key="attachments"/>
                    <entry key="flow" value="AccessRequest"/>
                    <entry key="id" value="c0a800fc94cb1e358194ccac8aec282a"/>
                    <entry key="interface" value="LCM"/>
                    <entry key="operation" value="EntitlementAdd"/>
                    <entry key="provisioningTransactionId" value="c0a81d89953c136081953d3334ee0279"/>
                  </Map>
                </Attributes>
                <AttributeRequest displayValue="AccountsReceivable" name="memberOf" op="Add" value="CN=AccountsReceivable,OU=Groups,OU=Demo,DC=Eshiam,DC=com">
                  <Attributes>
                    <Map>
                      <entry key="assignment" value="true"/>
                    </Map>
                  </Attributes>
                </AttributeRequest>
                <ProvisioningResult>
                  <Errors>
                    <Message key="Connection timed out: connect" type="Error"/>
                  </Errors>
                </ProvisioningResult>
              </AccountRequest>
              <Attributes>
                <Map>
                  <entry key="identityRequestId" value="0000000557"/>
                  <entry key="inRetry">
                    <value>
                      <Boolean>true</Boolean>
                    </value>
                  </entry>
                  <entry key="requester" value="spadmin"/>
                  <entry key="source" value="LCM"/>
                </Map>
              </Attributes>
              <Requesters>
                <Reference class="sailpoint.object.Identity" name="spadmin"/>
              </Requesters>
            </ProvisioningPlan>
            <ProvisioningPlan nativeIdentity="Carmen Hansen" targetIntegration="ProvisionIntegrMod" trackingId="69794e810d5847528110b910cc03b45b">
              <AccountRequest application="IntConApplication" nativeIdentity="1c2c3c4d" op="Create" targetIntegration="ProvisionIntegrMod">
                <Attributes>
                  <Map>
                    <entry key="attachmentConfigList"/>
                    <entry key="attachments"/>
                    <entry key="flow" value="AccessRequest"/>
                    <entry key="id" value="c0a800fb95361b21819538added109f7"/>
                    <entry key="interface" value="LCM"/>
                    <entry key="nativeIdUpdated">
                      <value>
                        <Boolean>true</Boolean>
                      </value>
                    </entry>
                    <entry key="operation" value="EntitlementAdd"/>
                    <entry key="provisioningTransactionId" value="c0a81d89953c136081953d333551027a"/>
                  </Map>
                </Attributes>
                <AttributeRequest displayValue="GroupName1" name="GroupId" op="Add" value="GIC1">
                  <Attributes>
                    <Map>
                      <entry key="assignment" value="true"/>
                    </Map>
                  </Attributes>
                </AttributeRequest>
                <AttributeRequest name="Name" op="Set" value="Carmen Hansen"/>
                <AttributeRequest name="FirstName" op="Set" value="Carmen"/>
                <AttributeRequest name="LastName" op="Set" value="Hansen"/>
                <AttributeRequest name="Department" op="Set" value="Finance"/>
                <AttributeRequest name="Email" op="Set" value="Carmen.Hansen@eshiam.com"/>
                <AttributeRequest name="manager" op="Set" value="Victor Pierce"/>
              </AccountRequest>
              <Attributes>
                <Map>
                  <entry key="identityRequestId" value="0000000557"/>
                  <entry key="requester" value="spadmin"/>
                  <entry key="source" value="LCM"/>
                </Map>
              </Attributes>
              <Requesters>
                <Reference class="sailpoint.object.Identity" name="spadmin"/>
              </Requesters>
              <ProvisioningResult status="committed"/>
            </ProvisioningPlan>
            <ProvisioningTarget application="IntConApplication" attribute="GroupId" value="GIC1">
              <AccountSelection applicationId="c0a8002394fb1f3081952339b50f2a6d" applicationName="IntConApplication" implicitCreate="true"/>
            </ProvisioningTarget>
            <ProvisioningTarget application="ActiveDirectory" attribute="memberOf" value="CN=AccountsReceivable,OU=Groups,OU=Demo,DC=Eshiam,DC=com">
              <AccountSelection applicationId="c0a800fc94cb1e358194cc6fcd4826a9" applicationName="ActiveDirectory" selection="CN=Carmen Hansen,OU=People,OU=Demo,DC=Eshiam,DC=com">
                <AccountInfo displayName="Carmen Hansen" nativeIdentity="CN=Carmen Hansen,OU=People,OU=Demo,DC=Eshiam,DC=com"/>
              </AccountSelection>
            </ProvisioningTarget>
          </ProvisioningProject>
        </value>
      </entry>
      <entry key="retries">
        <value>
          <Integer>0</Integer>
        </value>
      </entry>
      <entry key="workflowCaseId" value="c0a81d89953c136081953d32da070263"/>
      <entry key="workflowProcessId"/>
      <entry key="workflowSummary">
        <value>
          <WorkflowSummary step="end"/>
        </value>
      </entry>
    </Map>
  </Attributes>
  <Definition>
    <Reference class="sailpoint.object.TaskDefinition" name="Workflow Launcher"/>
  </Definition>
  <Messages>
    <Message key="Connection timed out: connect" type="Error"/>
    <Message key="Network is unreachable: connect" type="Error"/>
  </Messages>
  <Owner>
    <Reference class="sailpoint.object.Identity" name="spadmin"/>
  </Owner>
</TaskResult>