<?xml version='1.0' encoding='UTF-8'?>
<!DOCTYPE ManagedAttribute PUBLIC "sailpoint.dtd" "sailpoint.dtd">
<ManagedAttribute aggregated="true" attribute="memberOf" displayName="DataArchive" hash="7f35b233d900639b70dfef3ae543196d93c910ba" lastRefresh="1779697845043" requestable="true" type="group" uuid="{d4d3b6c4-e95f-43c6-80de-28b15f385339}" value="CN=DataArchive,OU=Groups,OU=Demo,DC=Eshiam,DC=com">
  <ApplicationRef>
    <Reference class="sailpoint.object.Application" name="ActiveDirectory"/>
  </ApplicationRef>
  <Attributes>
    <Map>
      <entry key="GroupScope" value="Global"/>
      <entry key="GroupType" value="Security"/>
      <entry key="NetBIOSName"/>
      <entry key="bundleLevel" value="IT"/>
      <entry key="cn" value="DataArchive"/>
      <entry key="msDS-PrincipalName" value="ESHIAM\DataArchive"/>
      <entry key="objectSid" value="S-1-5-21-2678700903-2778472132-3948167259-1124"/>
      <entry key="objectguid" value="{d4d3b6c4-e95f-43c6-80de-28b15f385339}"/>
      <entry key="sAMAccountName" value="DataArchive"/>
      <entry key="sysDescriptions">
        <value>
          <Map>
            <entry key="en_US"/>
          </Map>
        </value>
      </entry>
    </Map>
  </Attributes>
  <Owner>
    <Reference class="sailpoint.object.Identity" name="spadmin"/>
  </Owner>
</ManagedAttribute>