<?xml version='1.0' encoding='UTF-8'?>
<!DOCTYPE Link PUBLIC "sailpoint.dtd" "sailpoint.dtd">
<Link displayName="Jasmine Spence" identity="EMP00625" lastRefresh="1760088500966">
  <ApplicationRef>
    <Reference class="sailpoint.object.Application" name="HR2"/>
  </ApplicationRef>
  <Attributes>
    <Map>
      <entry key="Department" value="Customer Support"/>
      <entry key="Email" value="jasmine.spence@example.com"/>
      <entry key="EmployeeNo" value="EMP00625"/>
      <entry key="FirstName" value="Jasmine"/>
      <entry key="JoiningDate" value="2016-05-09"/>
      <entry key="LastName" value="Spence"/>
      <entry key="Name" value="Jasmine Spence"/>
      <entry key="NetworkID" value="jspence463"/>
    </Map>
  </Attributes>
</Link>