<?xml version='1.0' encoding='UTF-8'?>
<!DOCTYPE Link PUBLIC "sailpoint.dtd" "sailpoint.dtd">
<Link displayName="Michael Hester" identity="EMP00142" lastRefresh="1773139933955">
  <ApplicationRef>
    <Reference class="sailpoint.object.Application" name="HR2"/>
  </ApplicationRef>
  <Attributes>
    <Map>
      <entry key="Department" value="Admin"/>
      <entry key="Email" value="michael.hester@example.com"/>
      <entry key="EmployeeNo" value="EMP00142"/>
      <entry key="FirstName" value="Michael"/>
      <entry key="JoiningDate" value="2020-02-13"/>
      <entry key="LastName" value="Hester"/>
      <entry key="Name" value="Michael Hester"/>
      <entry key="NetworkID" value="mhester169"/>
    </Map>
  </Attributes>
</Link>