<?xml version='1.0' encoding='UTF-8'?>
<!DOCTYPE Link PUBLIC "sailpoint.dtd" "sailpoint.dtd">
<Link displayName="Timothy Anderson" identity="EMP00686" lastRefresh="1760088500966">
  <ApplicationRef>
    <Reference class="sailpoint.object.Application" name="HR2"/>
  </ApplicationRef>
  <Attributes>
    <Map>
      <entry key="Department" value="Finance"/>
      <entry key="Email" value="timothy.anderson@example.com"/>
      <entry key="EmployeeNo" value="EMP00686"/>
      <entry key="FirstName" value="Timothy"/>
      <entry key="JoiningDate" value="2019-05-03"/>
      <entry key="LastName" value="Anderson"/>
      <entry key="Name" value="Timothy Anderson"/>
      <entry key="NetworkID" value="tanderson445"/>
    </Map>
  </Attributes>
</Link>