<?xml version='1.0' encoding='UTF-8'?>
<!DOCTYPE Link PUBLIC "sailpoint.dtd" "sailpoint.dtd">
<Link displayName="Kathryn Johnston" identity="EMP01001" lastRefresh="1760088503096">
  <ApplicationRef>
    <Reference class="sailpoint.object.Application" name="HR2"/>
  </ApplicationRef>
  <Attributes>
    <Map>
      <entry key="Department" value="IT"/>
      <entry key="Email" value="kathryn.johnston@example.com"/>
      <entry key="EmployeeNo" value="EMP01001"/>
      <entry key="FirstName" value="Kathryn"/>
      <entry key="JoiningDate" value="2015-10-12"/>
      <entry key="LastName" value="Johnston"/>
      <entry key="Name" value="Kathryn Johnston"/>
      <entry key="NetworkID" value="kjohnston741"/>
    </Map>
  </Attributes>
</Link>