<?xml version='1.0' encoding='UTF-8'?>
<!DOCTYPE Link PUBLIC "sailpoint.dtd" "sailpoint.dtd">
<Link displayName="Alicia Davis" entitlements="true" identity="EMP00727" lastRefresh="1756877656326" manuallyCorrelated="true">
  <ApplicationRef>
    <Reference class="sailpoint.object.Application" name="WebServicesApplicationEshiam"/>
  </ApplicationRef>
  <Attributes>
    <Map>
      <entry key="department" value="Operations"/>
      <entry key="description" value="Created on Tue Aug 26 10:46:17 IST 2025"/>
      <entry key="groups">
        <value>
          <List>
            <String>WS_GROUP_101</String>
            <String>WS_GROUP_102</String>
          </List>
        </value>
      </entry>
      <entry key="location" value="India"/>
      <entry key="manager_id" value="1045"/>
      <entry key="user_email" value="alicia.davis@example.com"/>
      <entry key="user_id" value="EMP00727"/>
      <entry key="user_name" value="Alicia Davis"/>
      <entry key="user_status" value="ACTIVE"/>
    </Map>
  </Attributes>
</Link>