<?xml version='1.0' encoding='UTF-8'?>
<!DOCTYPE Link PUBLIC "sailpoint.dtd" "sailpoint.dtd">
<Link displayName="mahesh.nattali@eshiam.com" entitlements="true" identity="00ut8kbiyp2wEa78o697" lastRefresh="1752576033814">
  <ApplicationRef>
    <Reference class="sailpoint.object.Application" name="OktaApplication"/>
  </ApplicationRef>
  <Attributes>
    <Map>
      <entry key="IIQDisabled">
        <value>
          <Boolean/>
        </value>
      </entry>
      <entry key="IIQLocked">
        <value>
          <Boolean/>
        </value>
      </entry>
      <entry key="activated" value="2025-07-15T07:16:34.000Z"/>
      <entry key="applications">
        <value>
          <List>
            <String>0oat8kbiv1nDSDuk3697</String>
            <String>0oat8kbj5uBez3FRF697</String>
            <String>0oat8kn1xsqyUpO0P697</String>
            <String>0oat8kn201OA5QgJb697</String>
          </List>
        </value>
      </entry>
      <entry key="city" value="Hyderabad"/>
      <entry key="countryCode" value="IN"/>
      <entry key="created" value="2025-07-15T07:16:34.000Z"/>
      <entry key="department" value="Engineering"/>
      <entry key="displayName" value="Mahesh Nattali"/>
      <entry key="email" value="mahesh.nattali@eshiam.com"/>
      <entry key="employeeNumber" value="1045"/>
      <entry key="firstName" value="Mahesh"/>
      <entry key="groups">
        <value>
          <List>
            <String>00gt8kbiwma1Qb7KD697</String>
          </List>
        </value>
      </entry>
      <entry key="id" value="00ut8kbiyp2wEa78o697"/>
      <entry key="lastLogin" value="2025-07-15T10:27:50.000Z"/>
      <entry key="lastName" value="Nattali"/>
      <entry key="lastUpdated" value="2025-07-15T10:32:00.000Z"/>
      <entry key="login" value="mahesh.nattali@eshiam.com"/>
      <entry key="mobilePhone" value="8185906925"/>
      <entry key="passwordChanged" value="2025-07-15T07:17:27.000Z"/>
      <entry key="providerName" value="OKTA"/>
      <entry key="providerType" value="OKTA"/>
      <entry key="roles">
        <value>
          <List>
            <String>SUPER_ADMIN</String>
          </List>
        </value>
      </entry>
      <entry key="secondEmail"/>
      <entry key="state" value="Telangana"/>
      <entry key="status" value="ACTIVE"/>
      <entry key="statusChanged" value="2025-07-15T07:17:27.000Z"/>
    </Map>
  </Attributes>
</Link>