<?xml version='1.0' encoding='UTF-8'?>
<!DOCTYPE IdentityRequestItem PUBLIC "sailpoint.dtd" "sailpoint.dtd">
<IdentityRequestItem application="IntConApplication" compilationStatus="Expansion" nativeIdentity="EMP01053" operation="Create" provisioningEngine="ProvisionIntegrMod" provisioningState="Pending">
  <Attributes>
    <Map>
      <entry key="attachmentConfigList"/>
      <entry key="attachments"/>
      <entry key="flow" value="AccessRequest"/>
      <entry key="id" value="c0a800fb954110f0819541b0da4c00c3"/>
      <entry key="interface" value="LCM"/>
      <entry key="nativeIdUpdated">
        <value>
          <Boolean>true</Boolean>
        </value>
      </entry>
      <entry key="operation" value="Add"/>
      <entry key="provisioningPlan">
        <value>
          <ProvisioningPlan trackingId="c94bd9faec674bb083321642e726dbbd">
            <AccountRequest application="IntConApplication" nativeIdentity="EMP01053" op="Create" targetIntegration="ProvisionIntegrMod" trackingId="d9850b3a657048fabd8bd4072a66a960">
              <Attributes>
                <Map>
                  <entry key="attachmentConfigList"/>
                  <entry key="attachments"/>
                  <entry key="flow" value="AccessRequest"/>
                  <entry key="id" value="c0a800fb954110f0819541b0da4c00c3"/>
                  <entry key="interface" value="LCM"/>
                  <entry key="nativeIdUpdated">
                    <value>
                      <Boolean>true</Boolean>
                    </value>
                  </entry>
                  <entry key="operation" value="Add"/>
                  <entry key="provisioningTransactionId" value="c0a8003d96cf19858196ec42d71c195c"/>
                  <entry key="requester" value="spadmin"/>
                </Map>
              </Attributes>
            </AccountRequest>
            <Attributes>
              <Map>
                <entry key="source" value="LCM"/>
              </Map>
            </Attributes>
          </ProvisioningPlan>
        </value>
      </entry>
      <entry key="requester" value="spadmin"/>
    </Map>
  </Attributes>
</IdentityRequestItem>