<?xml version='1.0' encoding='UTF-8'?>
<!DOCTYPE Custom PUBLIC "sailpoint.dtd" "sailpoint.dtd">
<Custom name="Custom-Delimited Application Files">
  <Attributes>
    <Map>
      <entry key="TRE-TCR_Treasury-Client-Reconciliation-and-Reporting">
        <value>
          <Map>
            <entry key="InputFile">
              <value>
                <List>
                  <String>TRE-TCR-ICAM_Daily 1.csv</String>
                  <String>TRE-TCR-ICAM_Monthly 1.csv</String>
                </List>
              </value>
            </entry>
            <entry key="TargetFile" value="TRE-TCR.csv"/>
          </Map>
        </value>
      </entry>
    </Map>
  </Attributes>
</Custom>