<?xml version='1.0' encoding='UTF-8'?>
<!DOCTYPE IdentitySnapshot PUBLIC "sailpoint.dtd" "sailpoint.dtd">
<IdentitySnapshot applications="HR2" identityName="Katherine Hill">
  <Attributes>
    <Map>
      <entry key="department" value="Marketing"/>
      <entry key="displayName" value="Katherine Hill"/>
      <entry key="email" value="katherine.hill@example.com"/>
      <entry key="employeeId" value="EMP00155"/>
      <entry key="firstname" value="Katherine"/>
      <entry key="inactive">
        <value>
          <Boolean/>
        </value>
      </entry>
      <entry key="lastname" value="Hill"/>
      <entry key="networkId" value="khill182"/>
    </Map>
  </Attributes>
  <LinkSnapshots>
    <LinkSnapshot application="HR2" identity="EMP00155" lastRefresh="1751886995726" simpleIdentity="Katherine Hill">
      <Attributes>
        <Map>
          <entry key="Department" value="Marketing"/>
          <entry key="Email" value="katherine.hill@example.com"/>
          <entry key="EmployeeNo" value="EMP00155"/>
          <entry key="FirstName" value="Katherine"/>
          <entry key="JoiningDate" value="2019-05-27"/>
          <entry key="LastName" value="Hill"/>
          <entry key="Name" value="Katherine Hill"/>
          <entry key="NetworkID" value="khill182"/>
        </Map>
      </Attributes>
    </LinkSnapshot>
  </LinkSnapshots>
  <Scorecard/>
</IdentitySnapshot>