<?xml version='1.0' encoding='UTF-8'?>
<!DOCTYPE IdentitySnapshot PUBLIC "sailpoint.dtd" "sailpoint.dtd">
<IdentitySnapshot applications="HR-ApplicationTarget, JDBC, LDAPApplication, ActiveDirectory, HR-Application" identityName="Julie Graham" summary="ITLDAP-Engineering">
  <Attributes>
    <Map>
      <entry key="costCenter">
        <value>
          <List>
            <String>R01e, L01e</String>
          </List>
        </value>
      </entry>
      <entry key="department" value="Engineering"/>
      <entry key="displayName" value="Julie Graham"/>
      <entry key="email" value="Julie.Graham@eshiam.com"/>
      <entry key="employeeId" value="1b2a3c4b"/>
      <entry key="firstname" value="Julie"/>
      <entry key="lastname" value="Graham"/>
      <entry key="manager" value="Patrick Jenkins"/>
      <entry key="networkId" value="Julie.Graham"/>
      <entry key="region" value="Europe"/>
      <entry key="type" value="employee"/>
    </Map>
  </Attributes>
  <BundleSnapshots>
    <BundleSnapshot name="ITLDAP-Engineering">
      <Entitlements>
        <EntitlementSnapshot application="LDAPApplication" nativeIdentity="cn=Julie.Graham,ou=People,dc=my-domain,dc=com">
          <Attributes>
            <Map>
              <entry key="groups">
                <value>
                  <Set>
                    <String>cn=Employees,ou=Group,dc=my-domain,dc=com</String>
                    <String>cn=Managers,ou=Group,dc=my-domain,dc=com</String>
                  </Set>
                </value>
              </entry>
            </Map>
          </Attributes>
        </EntitlementSnapshot>
      </Entitlements>
    </BundleSnapshot>
  </BundleSnapshots>
  <LinkSnapshots>
    <LinkSnapshot application="HR-ApplicationTarget" identity="1b2a3c4b" lastRefresh="1714615484492" simpleIdentity="Julie Graham">
      <Attributes>
        <Map>
          <entry key="Department" value="Engineering"/>
          <entry key="Email" value="Julie.Graham@eshiam.com"/>
          <entry key="EmployeeNo" value="1b2a3c4b"/>
          <entry key="FirstName" value="Julie"/>
          <entry key="LastName" value="Graham"/>
          <entry key="Name" value="Julie Graham"/>
          <entry key="NetworkID" value="Julie.Graham"/>
          <entry key="manager" value="1b2a3c"/>
        </Map>
      </Attributes>
    </LinkSnapshot>
    <LinkSnapshot application="JDBC" identity="1b2a3c4b" lastRefresh="1714616258516" simpleIdentity="Julie Graham">
      <Attributes>
        <Map>
          <entry key="Department" value="Engineering"/>
          <entry key="Email" value="Julie.Graham@eshiam.com"/>
          <entry key="EmployeeNo" value="1b2a3c4b"/>
          <entry key="FirstName" value="Julie"/>
          <entry key="LastName" value="Graham"/>
          <entry key="Name" value="Julie Graham"/>
          <entry key="NetworkID" value="Julie.Graham"/>
          <entry key="manager" value="1b2a3c"/>
        </Map>
      </Attributes>
    </LinkSnapshot>
    <LinkSnapshot application="LDAPApplication" identity="cn=Julie.Graham,ou=People,dc=my-domain,dc=com" lastRefresh="1719333217731" simpleIdentity="Julie.Graham">
      <Attributes>
        <Map>
          <entry key="IIQDisabled">
            <value>
              <Boolean>true</Boolean>
            </value>
          </entry>
          <entry key="businessCategory" value="Inactive"/>
          <entry key="cn" value="Julie.Graham"/>
          <entry key="dn" value="cn=Julie.Graham,ou=People,dc=my-domain,dc=com"/>
          <entry key="groups">
            <value>
              <List>
                <String>cn=Employees,ou=Group,dc=my-domain,dc=com</String>
                <String>cn=Managers,ou=Group,dc=my-domain,dc=com</String>
              </List>
            </value>
          </entry>
          <entry key="objectClass">
            <value>
              <List>
                <String>inetOrgPerson</String>
              </List>
            </value>
          </entry>
          <entry key="sn" value="Graham"/>
        </Map>
      </Attributes>
    </LinkSnapshot>
    <LinkSnapshot application="ActiveDirectory" identity="CN=Julie Graham,OU=People,OU=Demo,DC=Eshiam,DC=com" lastRefresh="1741582379167" simpleIdentity="Julie Graham">
      <Attributes>
        <Map>
          <entry key="NetBIOSName"/>
          <entry key="accountFlags">
            <value>
              <List>
                <String>Normal User Account</String>
              </List>
            </value>
          </entry>
          <entry key="cn" value="Julie Graham"/>
          <entry key="department" value="Engineering"/>
          <entry key="displayName" value="Graham, Julie"/>
          <entry key="distinguishedName" value="CN=Julie Graham,OU=People,OU=Demo,DC=Eshiam,DC=com"/>
          <entry key="employeeID" value="1b2a3c4b"/>
          <entry key="givenName" value="Julie"/>
          <entry key="mail" value="Julie.Graham@eshiam.com"/>
          <entry key="memberOf"/>
          <entry key="msDS-PrincipalName" value="ESHIAM\Julie Graham"/>
          <entry key="msNPAllowDialin" value="Not Set"/>
          <entry key="objectClass">
            <value>
              <List>
                <String>top</String>
                <String>person</String>
                <String>organizationalPerson</String>
                <String>user</String>
              </List>
            </value>
          </entry>
          <entry key="objectSid" value="S-1-5-21-2678700903-2778472132-3948167259-1261"/>
          <entry key="objectType" value="user"/>
          <entry key="objectguid" value="{e0906738-11a9-424d-b16f-8caa488a23d1}"/>
          <entry key="sAMAccountName" value="Julie Graham"/>
          <entry key="sn" value="Graham"/>
          <entry key="userPrincipalName" value="Julie Graham@test.eshiam.com"/>
        </Map>
      </Attributes>
    </LinkSnapshot>
    <LinkSnapshot application="HR-Application" identity="1b2a3c4b" lastRefresh="1714564676577" simpleIdentity="Julie Graham">
      <Attributes>
        <Map>
          <entry key="Department" value="Engineering"/>
          <entry key="Email" value="Julie.Graham@eshiam.com"/>
          <entry key="EmployeeNo" value="1b2a3c4b"/>
          <entry key="FirstName" value="Julie"/>
          <entry key="LastName" value="Graham"/>
          <entry key="Name" value="Julie Graham"/>
          <entry key="NetworkID" value="Julie.Graham"/>
          <entry key="manager" value="1b2a3c"/>
        </Map>
      </Attributes>
    </LinkSnapshot>
  </LinkSnapshots>
  <Scorecard/>
</IdentitySnapshot>