<?xml version='1.0' encoding='UTF-8'?>
<!DOCTYPE IdentitySnapshot PUBLIC "sailpoint.dtd" "sailpoint.dtd">
<IdentitySnapshot applications="HR2" identityName="John Spears">
  <Attributes>
    <Map>
      <entry key="department" value="Admin"/>
      <entry key="displayName" value="John Spears"/>
      <entry key="email" value="john.spears@example.com"/>
      <entry key="employeeId" value="EMP01225"/>
      <entry key="firstname" value="John"/>
      <entry key="inactive">
        <value>
          <Boolean/>
        </value>
      </entry>
      <entry key="lastname" value="Spears"/>
      <entry key="networkId" value="jspears459"/>
    </Map>
  </Attributes>
  <LinkSnapshots>
    <LinkSnapshot application="HR2" identity="EMP01225" lastRefresh="1751887000556" simpleIdentity="John Spears">
      <Attributes>
        <Map>
          <entry key="Department" value="Admin"/>
          <entry key="Email" value="john.spears@example.com"/>
          <entry key="EmployeeNo" value="EMP01225"/>
          <entry key="FirstName" value="John"/>
          <entry key="JoiningDate" value="2023-01-16"/>
          <entry key="LastName" value="Spears"/>
          <entry key="Name" value="John Spears"/>
          <entry key="NetworkID" value="jspears459"/>
        </Map>
      </Attributes>
    </LinkSnapshot>
  </LinkSnapshots>
  <Scorecard/>
</IdentitySnapshot>