<?xml version='1.0' encoding='UTF-8'?>
<!DOCTYPE IdentitySnapshot PUBLIC "sailpoint.dtd" "sailpoint.dtd">
<IdentitySnapshot applications="HR2" identityName="Juan Hernandez">
  <Attributes>
    <Map>
      <entry key="department" value="Marketing"/>
      <entry key="displayName" value="Juan Hernandez"/>
      <entry key="email" value="juan.hernandez@example.com"/>
      <entry key="employeeId" value="EMP00381"/>
      <entry key="firstname" value="Juan"/>
      <entry key="inactive">
        <value>
          <Boolean/>
        </value>
      </entry>
      <entry key="lastname" value="Hernandez"/>
      <entry key="networkId" value="jhernandez953"/>
    </Map>
  </Attributes>
  <LinkSnapshots>
    <LinkSnapshot application="HR2" identity="EMP00381" lastRefresh="1751886995726" simpleIdentity="Juan Hernandez">
      <Attributes>
        <Map>
          <entry key="Department" value="Marketing"/>
          <entry key="Email" value="juan.hernandez@example.com"/>
          <entry key="EmployeeNo" value="EMP00381"/>
          <entry key="FirstName" value="Juan"/>
          <entry key="JoiningDate" value="2023-07-10"/>
          <entry key="LastName" value="Hernandez"/>
          <entry key="Name" value="Juan Hernandez"/>
          <entry key="NetworkID" value="jhernandez953"/>
        </Map>
      </Attributes>
    </LinkSnapshot>
  </LinkSnapshots>
  <Scorecard/>
</IdentitySnapshot>