<?xml version='1.0' encoding='UTF-8'?>
<!DOCTYPE IdentityRequest PUBLIC "sailpoint.dtd" "sailpoint.dtd">
<IdentityRequest completionStatus="Success" endDate="1737448555777" executionStatus="Completed" name="0000000429" priority="Normal" requesterDisplayName="The Administrator" requesterId="c0a81d898f331ca3818f33fcf64800ff" source="LCM" state="End" targetClass="Identity" targetDisplayName="Aiden markram" type="AccessRequest" verified="1737773486953">
  <Attributes>
    <Map>
      <entry key="provisionedProject">
        <value>
          <ProvisioningProject identity="Aiden markram">
            <Attributes>
              <Map>
                <entry key="disableRetryRequest">
                  <value>
                    <Boolean>true</Boolean>
                  </value>
                </entry>
                <entry key="identityRequestId" value="0000000429"/>
                <entry key="optimisticProvisioning" value="false"/>
                <entry key="requester" value="spadmin"/>
                <entry key="source" value="LCM"/>
              </Map>
            </Attributes>
            <ExpansionItems>
              <ExpansionItem application="IIQ" cause="Role" name="Capabilities" operation="Retain" sourceInfo="IT2ADEngineering" value="SyslogAdministrator"/>
            </ExpansionItems>
            <MasterPlan>
              <ProvisioningPlan>
                <AccountRequest application="ActiveDirectory" nativeIdentity="CN=Aiden markram,OU=People,OU=Demo,DC=Eshiam,DC=com" op="Modify">
                  <Attributes>
                    <Map>
                      <entry key="attachmentConfigList"/>
                      <entry key="attachments"/>
                      <entry key="flow" value="AccessRequest"/>
                      <entry key="id" value="c0a81d898f3419e3818f3439c70c0228"/>
                      <entry key="interface" value="LCM"/>
                      <entry key="operation" value="EntitlementAdd"/>
                    </Map>
                  </Attributes>
                  <AttributeRequest displayValue="AccountsReceivable" name="memberOf" op="Add" value="CN=AccountsReceivable,OU=Groups,OU=Demo,DC=Eshiam,DC=com">
                    <Attributes>
                      <Map>
                        <entry key="assignment" value="true"/>
                      </Map>
                    </Attributes>
                  </AttributeRequest>
                </AccountRequest>
                <Attributes>
                  <Map>
                    <entry key="identityRequestId" value="0000000429"/>
                    <entry key="requester" value="spadmin"/>
                    <entry key="source" value="LCM"/>
                  </Map>
                </Attributes>
                <ProvisioningTargets>
                  <ProvisioningTarget application="ActiveDirectory" attribute="memberOf" value="CN=AccountsReceivable,OU=Groups,OU=Demo,DC=Eshiam,DC=com">
                    <AccountSelection applicationId="c0a81d898f3419e3818f3430348a0119" applicationName="ActiveDirectory" selection="CN=Aiden markram,OU=People,OU=Demo,DC=Eshiam,DC=com">
                      <AccountInfo displayName="Aiden markram" nativeIdentity="CN=Aiden markram,OU=People,OU=Demo,DC=Eshiam,DC=com"/>
                    </AccountSelection>
                  </ProvisioningTarget>
                  <ProvisioningTarget retain="true" role="IT2ADEngineering">
                    <AccountSelection applicationId="c0a81d898f3419e3818f3430348a0119" applicationName="ActiveDirectory" selection="CN=Aiden markram,OU=People,OU=Demo,DC=Eshiam,DC=com">
                      <AccountInfo displayName="Aiden markram" nativeIdentity="CN=Aiden markram,OU=People,OU=Demo,DC=Eshiam,DC=com"/>
                    </AccountSelection>
                  </ProvisioningTarget>
                </ProvisioningTargets>
              </ProvisioningPlan>
            </MasterPlan>
            <ProvisioningPlan nativeIdentity="Aiden markram" targetIntegration="ActiveDirectory" trackingId="161cf298765a433dbd89ccfe0ecacd86">
              <AccountRequest application="ActiveDirectory" nativeIdentity="CN=Aiden markram,OU=People,OU=Demo,DC=Eshiam,DC=com" op="Modify" targetIntegration="ActiveDirectory">
                <Attributes>
                  <Map>
                    <entry key="attachmentConfigList"/>
                    <entry key="attachments"/>
                    <entry key="flow" value="AccessRequest"/>
                    <entry key="id" value="c0a81d898f3419e3818f3439c70c0228"/>
                    <entry key="interface" value="LCM"/>
                    <entry key="oldNativeIdentity" value="CN=Aiden markram,OU=People,OU=Demo,DC=Eshiam,DC=com"/>
                    <entry key="operation" value="Add"/>
                    <entry key="provisioningTransactionId" value="c0a800fb94691e9b81948800fffb12ef"/>
                    <entry key="requester" value="spadmin"/>
                    <entry key="uuid" value="{ce36c38f-25b5-41a3-8f69-2d6e3866eb32}"/>
                  </Map>
                </Attributes>
                <AttributeRequest displayValue="AccountsReceivable" name="memberOf" op="Add" value="CN=AccountsReceivable,OU=Groups,OU=Demo,DC=Eshiam,DC=com">
                  <Attributes>
                    <Map>
                      <entry key="assignment" value="true"/>
                    </Map>
                  </Attributes>
                </AttributeRequest>
                <ProvisioningResult status="committed"/>
              </AccountRequest>
              <Attributes>
                <Map>
                  <entry key="identityRequestId" value="0000000429"/>
                  <entry key="requester" value="spadmin"/>
                  <entry key="source" value="LCM"/>
                </Map>
              </Attributes>
            </ProvisioningPlan>
            <ProvisioningTarget application="ActiveDirectory" attribute="memberOf" value="CN=AccountsReceivable,OU=Groups,OU=Demo,DC=Eshiam,DC=com">
              <AccountSelection applicationId="c0a81d898f3419e3818f3430348a0119" applicationName="ActiveDirectory" selection="CN=Aiden markram,OU=People,OU=Demo,DC=Eshiam,DC=com">
                <AccountInfo displayName="Aiden markram" nativeIdentity="CN=Aiden markram,OU=People,OU=Demo,DC=Eshiam,DC=com"/>
              </AccountSelection>
            </ProvisioningTarget>
            <ProvisioningTarget retain="true" role="IT2ADEngineering">
              <AccountSelection applicationId="c0a81d898f3419e3818f3430348a0119" applicationName="ActiveDirectory" selection="CN=Aiden markram,OU=People,OU=Demo,DC=Eshiam,DC=com">
                <AccountInfo displayName="Aiden markram" nativeIdentity="CN=Aiden markram,OU=People,OU=Demo,DC=Eshiam,DC=com"/>
              </AccountSelection>
            </ProvisioningTarget>
          </ProvisioningProject>
        </value>
      </entry>
      <entry key="taskResultId" value="c0a800fb94691e9b81948800f7ec12de"/>
    </Map>
  </Attributes>
  <RequestItems>
    <IdentityRequestItem application="ActiveDirectory" approvalState="Finished" name="memberOf" nativeIdentity="CN=Aiden markram,OU=People,OU=Demo,DC=Eshiam,DC=com" operation="Add" ownerName="spadmin" provisioningEngine="ActiveDirectory" provisioningState="Finished" value="CN=AccountsReceivable,OU=Groups,OU=Demo,DC=Eshiam,DC=com">
      <Attributes>
        <Map>
          <entry key="assignmentId" value="7bff7ed4556a4443a468e6aae9413388"/>
          <entry key="attachmentConfigList"/>
          <entry key="attachments"/>
          <entry key="flow" value="AccessRequest"/>
          <entry key="id" value="c0a81d898f3419e3818f3439c70c0228"/>
          <entry key="identityEntitlementId" value="c0a800fb94691e9b81948800fc5512eb"/>
          <entry key="interface" value="LCM"/>
          <entry key="managedAttributeType" value="Entitlement"/>
          <entry key="operation" value="EntitlementAdd"/>
          <entry key="provisioningPlan">
            <value>
              <ProvisioningPlan trackingId="4ebded7636d94faabf0550e977aea60a">
                <AccountRequest application="ActiveDirectory" nativeIdentity="CN=Aiden markram,OU=People,OU=Demo,DC=Eshiam,DC=com" op="Modify" targetIntegration="ActiveDirectory">
                  <Attributes>
                    <Map>
                      <entry key="attachmentConfigList"/>
                      <entry key="attachments"/>
                      <entry key="flow" value="AccessRequest"/>
                      <entry key="id" value="c0a81d898f3419e3818f3439c70c0228"/>
                      <entry key="interface" value="LCM"/>
                      <entry key="oldNativeIdentity" value="CN=Aiden markram,OU=People,OU=Demo,DC=Eshiam,DC=com"/>
                      <entry key="operation" value="Add"/>
                      <entry key="provisioningTransactionId" value="c0a800fb94691e9b81948800fffb12ef"/>
                      <entry key="requester" value="spadmin"/>
                      <entry key="uuid" value="{ce36c38f-25b5-41a3-8f69-2d6e3866eb32}"/>
                    </Map>
                  </Attributes>
                  <AttributeRequest displayValue="AccountsReceivable" name="memberOf" op="Add" trackingId="4ebded7636d94faabf0550e977aea60a" value="CN=AccountsReceivable,OU=Groups,OU=Demo,DC=Eshiam,DC=com">
                    <Attributes>
                      <Map>
                        <entry key="assignment" value="true"/>
                      </Map>
                    </Attributes>
                  </AttributeRequest>
                </AccountRequest>
                <Attributes>
                  <Map>
                    <entry key="source" value="LCM"/>
                  </Map>
                </Attributes>
              </ProvisioningPlan>
            </value>
          </entry>
        </Map>
      </Attributes>
      <Owner>
        <Reference class="sailpoint.object.Identity" name="spadmin"/>
      </Owner>
    </IdentityRequestItem>
  </RequestItems>
</IdentityRequest>